winzy_convert/__init__.py
winzy_convert-0.0.2.dist-info/licenses/LICENSE
winzy_convert-0.0.2.dist-info/METADATA
winzy_convert-0.0.2.dist-info/WHEEL
winzy_convert-0.0.2.dist-info/entry_points.txt
winzy_convert-0.0.2.dist-info/top_level.txt
winzy_convert-0.0.2.dist-info/RECORD
