Metadata-Version: 2.4
Name: winzy-convert
Version: 0.0.2
Summary: Mimic's convert to convert images to pdf, ppt etc.
Author: Sukhbinder Singh
License: Apache-2.0
Project-URL: Homepage, https://github.com/sukhbinder/winzy-convert
Project-URL: Changelog, https://github.com/sukhbinder/winzy-convert/releases
Project-URL: Issues, https://github.com/sukhbinder/winzy-convert/issues
Project-URL: CI, https://github.com/sukhbinder/winzy-convert/actions
Classifier: License :: OSI Approved :: Apache Software License
License-File: LICENSE
Requires-Dist: winzy
Requires-Dist: pillow
Provides-Extra: test
Requires-Dist: pytest; extra == "test"
Dynamic: license-file
